c64img/__init__.py
c64img/base.py
c64img/cmd_convert.py
c64img/hires.py
c64img/logger.py
c64img/multi.py
c64img/path.py
c64img-3.5.dist-info/LICENSE
c64img-3.5.dist-info/METADATA
c64img-3.5.dist-info/WHEEL
c64img-3.5.dist-info/entry_points.txt
c64img-3.5.dist-info/top_level.txt
c64img-3.5.dist-info/RECORD
