Metadata-Version: 2.1
Name: c64img
Version: 3.5
Summary: Image processing and converter for C64 graphic formats
Author-email: Roman Dobosz <gryf73@gmail.com>
License: BSD
Project-URL: Homepage, https://bitbucket.org/gryf/image2c64
Keywords: c64,image,converter,koala,Art Studio,raw
Classifier: Programming Language :: Python :: 3
Classifier: Programming Language :: Python :: 3.8
Classifier: Programming Language :: Python :: 3.9
Classifier: Programming Language :: Python :: 3.10
Classifier: Programming Language :: Python :: 3.11
Classifier: Programming Language :: Python :: 3 :: Only
Classifier: Development Status :: 5 - Production/Stable
Classifier: Environment :: Console
Classifier: Intended Audience :: End Users/Desktop
Classifier: License :: OSI Approved :: BSD License
Classifier: Operating System :: OS Independent
Classifier: Topic :: Multimedia :: Graphics
Classifier: Topic :: Multimedia :: Graphics :: Graphics Conversion
Requires-Python: >=3.8
License-File: LICENSE
Requires-Dist: Pillow >=10.3.0
